cachet_url_monitor/__init__.py
cachet_url_monitor/client.py
cachet_url_monitor/configuration.py
cachet_url_monitor/exceptions.py
cachet_url_monitor/expectation.py
cachet_url_monitor/latency_unit.py
cachet_url_monitor/scheduler.py
cachet_url_monitor/status.py
cachet_url_monitor/webhook.py
cachet_url_monitor/plugins/__init__.py
cachet_url_monitor/plugins/token_provider.py
cachet_url_monitor-0.6.10.dist-info/LICENSE
cachet_url_monitor-0.6.10.dist-info/METADATA
cachet_url_monitor-0.6.10.dist-info/WHEEL
cachet_url_monitor-0.6.10.dist-info/top_level.txt
cachet_url_monitor-0.6.10.dist-info/RECORD
