Metadata-Version: 2.1
Name: cachet-url-monitor
Version: 0.6.10
Summary: Cachet URL monitor plugin
Home-page: https://github.com/mtakaki/cachet-url-monitor
Author: Mitsuo Takaki
Author-email: mitsuotakaki@gmail.com
License: MIT
Platform: UNKNOWN
Requires: requests
Requires: PyYAML
Requires: Click
Requires: boto3
